Metadata-Version: 1.0
Name: odev
Version: 0.1.5
Summary: odev
Home-page: https://example.org
Author: me
Author-email: me@example.org
License: LGPL v3
Keywords: odev
Platform: UNKNOWN
